libpyvivotek/__init__.py
libpyvivotek/py.typed
libpyvivotek/vivotek.py
libpyvivotek-0.6.0.dist-info/licenses/LICENSE
tests/__init__.py
tests/test_vivotek_camera.py
libpyvivotek-0.6.0.dist-info/METADATA
libpyvivotek-0.6.0.dist-info/WHEEL
libpyvivotek-0.6.0.dist-info/top_level.txt
libpyvivotek-0.6.0.dist-info/RECORD
