Metadata-Version: 2.4
Name: libpyvivotek
Version: 0.6.0
Summary: Python Library for Vivotek IP Cameras
Author-email: Kevin McCormack <kevin@mccormack.tech>
License: LGPLv3+
Project-URL: Homepage, https://github.com/HarlemSquirrel/python-vivotek
Project-URL: Bug Tracker, https://github.com/HarlemSquirrel/python-vivotek/issues
Keywords: Camera,IPC,vivotek
Classifier: License :: OSI Approved :: MIT License
Classifier: Operating System :: OS Independent
Classifier: Programming Language :: Python :: 3
Requires-Python: >=3.10
License-File: LICENSE
Requires-Dist: requests
Provides-Extra: tests
Requires-Dist: pylint>=2.3; extra == "tests"
Requires-Dist: pytest; extra == "tests"
Requires-Dist: mypy>=1.18.1; extra == "tests"
Requires-Dist: vcrpy>=2.0; extra == "tests"
Dynamic: license-file
